lmdb_simple/__init__.py
lmdb_simple/core.py
lmdb_simple-0.1.3.dist-info/licenses/LICENSE
lmdb_simple-0.1.3.dist-info/METADATA
lmdb_simple-0.1.3.dist-info/WHEEL
lmdb_simple-0.1.3.dist-info/top_level.txt
lmdb_simple-0.1.3.dist-info/RECORD
