Metadata-Version: 2.4
Name: lmdb-simple
Version: 0.1.3
Summary: LMDB-backed dict-like store
Home-page: https://github.com/yourusername/lmdb-simple
Author: Your Name
Author-email: you@example.com
License: Apache-2.0
Classifier: Programming Language :: Python :: 3.9
Classifier: License :: OSI Approved :: Apache Software License
Classifier: Operating System :: OS Independent
Requires-Python: >=3.9
License-File: LICENSE
Requires-Dist: lmdb==1.6.2
Dynamic: author
Dynamic: author-email
Dynamic: classifier
Dynamic: description
Dynamic: description-content-type
Dynamic: home-page
Dynamic: license
Dynamic: license-file
Dynamic: requires-dist
Dynamic: requires-python
Dynamic: summary
